[{"id":"k9xpdimu","material":"D","rim":"shield","rank":14,"dp":5251,"pp":18055,"blunt":100,"edged":100,"piercing":100,"parent1":"k9xpdelq","parent2":"k9xpd9zj","sources":{"D-shield-5":3,"W-shield-2":516,"W-shield-3":348,"W-shield-5":84}},{"id":"k9xpdelq","material":"D","rim":"shield","rank":13,"dp":5271,"pp":18056,"blunt":72,"edged":72,"piercing":72,"parent1":"k9xpd9zj","parent2":"k9xpd7c0","sources":{"D-shield-5":2,"W-shield-2":314,"W-shield-3":212,"W-shield-5":51}},{"id":"k9xpd9zj","material":"D","rim":"shield","rank":12,"dp":5232,"pp":18055,"blunt":53,"edged":53,"piercing":53,"parent1":"k9xpd7c0","parent2":"k9xpcuz1","sources":{"D-shield-5":1,"W-shield-2":202,"W-shield-3":136,"W-shield-5":33}},{"id":"k9xpd7c0","material":"D","rim":"shield","rank":11,"dp":5310,"pp":18058,"blunt":37,"edged":37,"piercing":37,"parent1":"k9xp9m3a","parent2":"k9xpcuz1","sources":{"D-shield-5":1,"W-shield-2":112,"W-shield-3":76,"W-shield-5":18}},{"id":"k9xpcuz1","material":"W","rim":"shield","rank":10,"dp":5155,"pp":18052,"blunt":52,"edged":52,"piercing":52,"parent1":"k9xpckye","parent2":"k9xpbijh","sources":{"W-shield-2":90,"W-shield-3":60,"W-shield-5":15}},{"id":"k9xpckye","material":"W","rim":"shield","rank":10,"dp":5154,"pp":18058,"blunt":31,"edged":31,"piercing":31,"parent1":"k9xnvhea","parent2":"k9xnuzpd","sources":{"W-shield-2":40,"W-shield-3":28,"W-shield-5":7}},{"id":"k9xpbijh","material":"W","rim":"shield","rank":10,"dp":5156,"pp":18047,"blunt":34,"edged":34,"piercing":34,"parent1":"k9xnvhea","parent2":"k9xpbd4e","sources":{"W-shield-2":50,"W-shield-3":32,"W-shield-5":8}},{"id":"k9xpbd4e","material":"W","rim":"shield","rank":7,"dp":5159,"pp":18031,"blunt":22,"edged":22,"piercing":22,"parent1":"k9xnpnn3","parent2":"k9xnpnn3","sources":{"W-shield-2":28,"W-shield-3":16,"W-shield-5":4}},{"id":"k9xp9m3a","material":"D","rim":"shield","rank":9,"dp":5466,"pp":18064,"blunt":11,"edged":11,"piercing":11,"parent1":"k9xo1qho","parent2":"k9xnmf6t","sources":{"D-shield-5":1,"W-shield-2":22,"W-shield-3":16,"W-shield-5":3}},{"id":"k9xo1qho","material":"D","rim":"shield","rank":8,"dp":5780,"pp":18053,"blunt":10,"edged":10,"piercing":10,"parent1":"k9xo1kuz","parent2":"k9xnmf6t","sources":{"D-shield-5":1,"W-shield-2":18,"W-shield-3":12,"W-shield-5":2}},{"id":"k9xo1kuz","material":"D","rim":"shield","rank":7,"dp":6409,"pp":18031,"blunt":9,"edged":9,"piercing":9,"parent1":"k9xo17qk","parent2":"k9xnmf6t","sources":{"D-shield-5":1,"W-shield-2":14,"W-shield-3":8,"W-shield-5":1}},{"id":"k9xo17qk","material":"D","rim":"shield","rank":5,"dp":7666,"pp":17987,"blunt":6,"edged":6,"piercing":6,"parent1":"D-shield-5","parent2":"k9xnp51y","sources":{"D-shield-5":1,"W-shield-2":10,"W-shield-3":4}},{"id":"k9xny4xe","material":"W","rim":"shield","rank":14,"dp":5154,"pp":18052,"blunt":100,"edged":100,"piercing":100,"parent1":"k9xny1sy","parent2":"k9xnxzar","sources":{"W-shield-2":246,"W-shield-3":168,"W-shield-5":42}},{"id":"k9xny1sy","material":"W","rim":"shield","rank":13,"dp":5154,"pp":18053,"blunt":73,"edged":73,"piercing":73,"parent1":"k9xnxzar","parent2":"k9xnxvto","sources":{"W-shield-2":152,"W-shield-3":104,"W-shield-5":26}},{"id":"k9xnxzar","material":"W","rim":"shield","rank":12,"dp":5155,"pp":18051,"blunt":53,"edged":53,"piercing":53,"parent1":"k9xnxvto","parent2":"k9xnvt6i","sources":{"W-shield-2":94,"W-shield-3":64,"W-shield-5":16}},{"id":"k9xnxvto","material":"W","rim":"shield","rank":11,"dp":5154,"pp":18055,"blunt":39,"edged":39,"piercing":39,"parent1":"k9xnvt6i","parent2":"k9xnvhea","sources":{"W-shield-2":58,"W-shield-3":40,"W-shield-5":10}},{"id":"k9xnvt6i","material":"W","rim":"shield","rank":10,"dp":5156,"pp":18047,"blunt":28,"edged":28,"piercing":28,"parent1":"k9xnvhea","parent2":"k9xnpnn3","sources":{"W-shield-2":36,"W-shield-3":24,"W-shield-5":6}},{"id":"k9xnvhea","material":"W","rim":"shield","rank":9,"dp":5153,"pp":18064,"blunt":21,"edged":21,"piercing":21,"parent1":"k9xnuzpd","parent2":"k9xnmf6t","sources":{"W-shield-2":22,"W-shield-3":16,"W-shield-5":4}},{"id":"k9xnuzpd","material":"W","rim":"shield","rank":8,"dp":5155,"pp":18053,"blunt":18,"edged":18,"piercing":18,"parent1":"k9xnpnn3","parent2":"k9xnmf6t","sources":{"W-shield-2":18,"W-shield-3":12,"W-shield-5":3}},{"id":"k9xnpnn3","material":"W","rim":"shield","rank":7,"dp":5159,"pp":18031,"blunt":14,"edged":14,"piercing":14,"parent1":"k9xnmf6t","parent2":"k9xnpf9q","sources":{"W-shield-2":14,"W-shield-3":8,"W-shield-5":2}},{"id":"k9xnpf9q","material":"W","rim":"shield","rank":5,"dp":5166,"pp":17987,"blunt":9,"edged":9,"piercing":9,"parent1":"k9xnp51y","parent2":"W-shield-5","sources":{"W-shield-2":10,"W-shield-3":4,"W-shield-5":1}},{"id":"k9xnp51y","material":"W","rim":"shield","rank":5,"dp":5042,"pp":18775,"blunt":0,"edged":15,"piercing":15,"parent1":"k9xnov3q","parent2":"k9xnm219","sources":{"W-shield-2":10,"W-shield-3":4}},{"id":"k9xnov3q","material":"W","rim":"shield","rank":4,"dp":5015,"pp":18950,"blunt":0,"edged":26,"piercing":9,"parent1":"k9xnor86","parent2":"k9xnm219","sources":{"W-shield-2":10,"W-shield-3":2}},{"id":"k9xnor86","material":"W","rim":"shield","rank":2,"dp":4960,"pp":19300,"blunt":0,"edged":44,"piercing":0,"parent1":"k9xno887","parent2":"k9xnlt1x","sources":{"W-shield-2":10}},{"id":"k9xno887","material":"W","rim":"shield","rank":2,"dp":4960,"pp":19300,"blunt":0,"edged":40,"piercing":0,"parent1":"k9xnlxc5","parent2":"k9xnlxc5","sources":{"W-shield-2":8}},{"id":"k9xnmf6t","material":"W","rim":"shield","rank":6,"dp":5152,"pp":18075,"blunt":9,"edged":9,"piercing":9,"parent1":"k9xnmb39","parent2":"W-shield-5","sources":{"W-shield-2":4,"W-shield-3":4,"W-shield-5":1}},{"id":"k9xnmb39","material":"W","rim":"shield","rank":4,"dp":5015,"pp":18950,"blunt":0,"edged":15,"piercing":15,"parent1":"k9xnlxc5","parent2":"k9xnm62m","sources":{"W-shield-2":4,"W-shield-3":4}},{"id":"k9xnm62m","material":"W","rim":"shield","rank":3,"dp":5070,"pp":18600,"blunt":0,"edged":0,"piercing":25,"parent1":"k9xnm219","parent2":"k9xnm219","sources":{"W-shield-3":4}},{"id":"k9xnm219","material":"W","rim":"shield","rank":3,"dp":5070,"pp":18600,"blunt":0,"edged":0,"piercing":16,"parent1":"W-shield-3","parent2":"W-shield-3","sources":{"W-shield-3":2}},{"id":"k9xnlxc5","material":"W","rim":"shield","rank":2,"dp":4960,"pp":19300,"blunt":0,"edged":25,"piercing":0,"parent1":"k9xnlt1x","parent2":"k9xnlt1x","sources":{"W-shield-2":4}},{"id":"k9xnlt1x","material":"W","rim":"shield","rank":2,"dp":4960,"pp":19300,"blunt":0,"edged":16,"piercing":0,"parent1":"W-shield-2","parent2":"W-shield-2","sources":{"W-shield-2":2}}]